[
  {
    "id": "node/462590758",
    "name": "Fruits et Légumes RG",
    "lat": 47.0938468,
    "lng": -70.327937,
    "type": "farm",
    "website": null
  },
  {
    "id": "node/469867191",
    "name": "Cidrerie Le Somnambule",
    "lat": 46.6619084,
    "lng": -71.0765364,
    "type": "farm",
    "website": null
  },
  {
    "id": "prod-012",
    "name": "Boucherie du Lac",
    "lat": 46.9,
    "lng": -71.2,
    "type": "farm",
    "website": "https://boucheriedulac.ca"
  },
  {
    "id": "node/947592289",
    "name": "Le Cep d'Argent",
    "lat": 45.2912118,
    "lng": -72.0561952,
    "type": "winery",
    "website": "https://www.cepdargent.com/"
  },
  {
    "id": "node/1294534786",
    "name": "La Fruiteraie des Gadbois",
    "lat": 45.4432377,
    "lng": -73.0632586,
    "type": "farm",
    "website": "https://lafruiteraie.com/"
  },
  {
    "id": "node/1344056806",
    "name": "Le magasin",
    "lat": 48.2395286,
    "lng": -70.1966212,
    "type": "farm",
    "website": null
  },
  {
    "id": "node/1700245168",
    "name": "Bleuetière l’Or Bleu",
    "lat": 45.0601912,
    "lng": -72.0617632,
    "type": "farm",
    "website": null
  },
  {
    "id": "node/1816150081",
    "name": "M Blé D'inde",
    "lat": 46.1621616,
    "lng": -74.7070108,
    "type": "farm",
    "website": null
  },
  {
    "id": "node/2018091043",
    "name": "Vignoble Clos St-Ignace",
    "lat": 46.0929795,
    "lng": -73.1173877,
    "type": "winery",
    "website": null
  },
  {
    "id": "node/2400999716",
    "name": "Le Barbocheux",
    "lat": 47.4128877,
    "lng": -61.7905464,
    "type": "winery",
    "website": null
  },
  {
    "id": "node/2584459098",
    "name": "Petch's Orchard",
    "lat": 45.0461259,
    "lng": -73.5961223,
    "type": "farm",
    "website": null
  },
  {
    "id": "node/4109497489",
    "name": "Cidrerie Verger Ferland",
    "lat": 45.2415039,
    "lng": -71.856537,
    "type": "farm",
    "website": null
  },
  {
    "id": "node/4337070670",
    "name": "Fruiterie St-Donat",
    "lat": 46.3198128,
    "lng": -74.223983,
    "type": "farm",
    "website": null
  },
  {
    "id": "node/4409660842",
    "name": "Ferme Bourdages Tradition",
    "lat": 48.0782669,
    "lng": -65.5936653,
    "type": "farm",
    "website": "http://fermebourdages.com/"
  },
  {
    "id": "node/4413315336",
    "name": "Cidrerie Michel Jodoin",
    "lat": 45.4568374,
    "lng": -73.0381738,
    "type": "winery",
    "website": null
  },
  {
    "id": "node/4565218500",
    "name": "Domaine Pinnacle",
    "lat": 45.0268508,
    "lng": -72.7843632,
    "type": "winery",
    "website": null
  },
  {
    "id": "node/4565218503",
    "name": "Verger Au Coeur De La Pomme",
    "lat": 45.0650155,
    "lng": -72.8533789,
    "type": "farm",
    "website": null
  },
  {
    "id": "node/4565219210",
    "name": "Vignoble de l'Orpailleur",
    "lat": 45.1098653,
    "lng": -72.8593664,
    "type": "winery",
    "website": null
  },
  {
    "id": "node/4565219212",
    "name": "Vignoble Gagliano",
    "lat": 45.1097782,
    "lng": -72.8564506,
    "type": "winery",
    "website": null
  },
  {
    "id": "node/4565219214",
    "name": "UNION LIBRE cidre & vin",
    "lat": 45.1091289,
    "lng": -72.8564956,
    "type": "winery",
    "website": null
  },
  {
    "id": "node/4565219215",
    "name": "Vignoble les Trois Clochers Enr.",
    "lat": 45.1257182,
    "lng": -72.8159134,
    "type": "winery",
    "website": null
  },
  {
    "id": "node/4565219216",
    "name": "Vignoble Centaure",
    "lat": 45.129706,
    "lng": -72.8012405,
    "type": "winery",
    "website": null
  },
  {
    "id": "node/4565744956",
    "name": "Vergers et Cidrerie Denis Charbonneau",
    "lat": 45.3476028,
    "lng": -73.1502327,
    "type": "winery",
    "website": null
  },
  {
    "id": "node/4569917946",
    "name": "Vignoble Pigeon Hill",
    "lat": 45.0403451,
    "lng": -72.9380554,
    "type": "winery",
    "website": null
  },
  {
    "id": "node/4574021090",
    "name": "Marché Fermier du comté de Huntingdon",
    "lat": 45.0888643,
    "lng": -74.1751995,
    "type": "farm",
    "website": null
  },
  {
    "id": "node/4596330520",
    "name": "Kiosque du Coin",
    "lat": 45.9536625,
    "lng": -73.5779831,
    "type": "farm",
    "website": null
  },
  {
    "id": "node/4618645648",
    "name": "Vignoble du Vent Maudit",
    "lat": 46.1160108,
    "lng": -73.2220071,
    "type": "winery",
    "website": null
  },
  {
    "id": "node/4661616878",
    "name": "Marché champêtre de North Hatley",
    "lat": 45.2784467,
    "lng": -71.9720551,
    "type": "farm",
    "website": null
  },
  {
    "id": "node/4677461180",
    "name": "Les Vergers de la Colline",
    "lat": 45.4835419,
    "lng": -72.7596182,
    "type": "farm",
    "website": "https://cidreriemilton.com/"
  },
  {
    "id": "node/4685699295",
    "name": "Le Domaine Perdu",
    "lat": 45.1190419,
    "lng": -72.6666577,
    "type": "winery",
    "website": null
  },
  {
    "id": "node/4716736456",
    "name": "Les Jardins de la Terre",
    "lat": 45.4197694,
    "lng": -72.9282614,
    "type": "farm",
    "website": "https://jardinsdelaterre.org"
  },
  {
    "id": "node/4734354907",
    "name": "Marché public de Saint-Jérôme",
    "lat": 45.7764411,
    "lng": -73.9989097,
    "type": "farm",
    "website": null
  },
  {
    "id": "node/4756216521",
    "name": "Domaine Neige",
    "lat": 45.0457332,
    "lng": -73.5710667,
    "type": "winery",
    "website": null
  },
  {
    "id": "node/4756216522",
    "name": "Vignoble Le Chat Botté",
    "lat": 45.0457306,
    "lng": -73.5673305,
    "type": "winery",
    "website": null
  },
  {
    "id": "node/4783356570",
    "name": "Vignoble Rivière du Chêne",
    "lat": 45.5637069,
    "lng": -73.9754427,
    "type": "winery",
    "website": null
  },
  {
    "id": "node/4847467588",
    "name": "La Belle Alliance",
    "lat": 45.3099105,
    "lng": -72.5551775,
    "type": "winery",
    "website": null
  },
  {
    "id": "node/4916823842",
    "name": "La Magie de la Pomme",
    "lat": 45.5695985,
    "lng": -74.0059519,
    "type": "farm",
    "website": null
  },
  {
    "id": "node/4964897022",
    "name": "Les Vallons de Wadleigh",
    "lat": 45.7230092,
    "lng": -72.2386592,
    "type": "winery",
    "website": null
  },
  {
    "id": "node/5058147796",
    "name": "Vignoble Lano d’Or",
    "lat": 45.9121405,
    "lng": -73.253342,
    "type": "winery",
    "website": null
  },
  {
    "id": "node/5315676706",
    "name": "Vignoble Domaine du Clos de L'Isle",
    "lat": 46.3448124,
    "lng": -72.4859988,
    "type": "winery",
    "website": null
  },
  {
    "id": "node/5418559222",
    "name": "Domaine les Brome Léon Courville",
    "lat": 45.2591189,
    "lng": -72.5924666,
    "type": "winery",
    "website": null
  },
  {
    "id": "node/5507881314",
    "name": "Vignoble de la Bauge",
    "lat": 45.2342304,
    "lng": -72.8542268,
    "type": "winery",
    "website": null
  },
  {
    "id": "node/5975908749",
    "name": "Lavender Ridge",
    "lat": 45.5231477,
    "lng": -75.9935769,
    "type": "farm",
    "website": null
  },
  {
    "id": "node/6165067017",
    "name": "Distillerie Fils du Roy Québec",
    "lat": 47.9155272,
    "lng": -69.4372633,
    "type": "distillery",
    "website": null
  },
  {
    "id": "node/6190935396",
    "name": "Cooperative La Mauve",
    "lat": 46.8924156,
    "lng": -70.8239859,
    "type": "farm",
    "website": null
  },
  {
    "id": "node/6195149181",
    "name": "Cidrerie Vergers Pedneault",
    "lat": 47.4212175,
    "lng": -70.3774765,
    "type": "winery",
    "website": null
  },
  {
    "id": "node/6264988298",
    "name": "Ferme la Chouette Lapone",
    "lat": 46.617033,
    "lng": -72.4863769,
    "type": "farm",
    "website": null
  },
  {
    "id": "node/6501154828",
    "name": "Little Red Wagon Winery",
    "lat": 45.6173615,
    "lng": -76.5342093,
    "type": "winery",
    "website": null
  },
  {
    "id": "node/6705077487",
    "name": "Les Herbes aux Soins",
    "lat": 45.9639452,
    "lng": -72.230692,
    "type": "farm",
    "website": "https://lesherbesauxsoins.ca/"
  },
  {
    "id": "node/7391324279",
    "name": "Ferme Avicole Bio-grain",
    "lat": 45.2745872,
    "lng": -73.2295693,
    "type": "farm",
    "website": "http://fermeavicolebio-grain.ca/"
  },
  {
    "id": "node/7495520340",
    "name": "Kiosque chez Forget",
    "lat": 45.6722011,
    "lng": -73.6010406,
    "type": "farm",
    "website": null
  },
  {
    "id": "node/7659702760",
    "name": "Les jardins Mistook",
    "lat": 48.6272744,
    "lng": -71.6781006,
    "type": "farm",
    "website": null
  },
  {
    "id": "node/7777892755",
    "name": "Ferme des Petits Cailloux",
    "lat": 45.0392456,
    "lng": -73.8749695,
    "type": "farm",
    "website": "https://fermedespetitscailloux.com/"
  },
  {
    "id": "node/7920739322",
    "name": "Vignoble Leblanc",
    "lat": 45.1412416,
    "lng": -74.3448606,
    "type": "winery",
    "website": null
  },
  {
    "id": "node/8003699683",
    "name": "Les Bleuets du Marquis",
    "lat": 45.0703929,
    "lng": -72.4519365,
    "type": "farm",
    "website": null
  },
  {
    "id": "node/8122047532",
    "name": "Mosti Mondiale",
    "lat": 45.3942858,
    "lng": -73.6008228,
    "type": "wine",
    "website": null
  },
  {
    "id": "node/8157957772",
    "name": "Kiosque Sylvain",
    "lat": 45.4972689,
    "lng": -74.0250988,
    "type": "farm",
    "website": null
  },
  {
    "id": "node/8166176867",
    "name": "Les viandes AMS",
    "lat": 45.4118738,
    "lng": -73.490577,
    "type": "meat",
    "website": null
  },
  {
    "id": "node/8272743739",
    "name": "La Chaufferie",
    "lat": 45.3972856,
    "lng": -72.7274582,
    "type": "distillery",
    "website": "https://lachaufferie.ca/"
  },
  {
    "id": "node/8292085281",
    "name": "Les jardins de Hatley",
    "lat": 45.3036756,
    "lng": -71.9766162,
    "type": "farm",
    "website": null
  },
  {
    "id": "node/8331717187",
    "name": "Kiosque Joli-Bois Fruit et Légume",
    "lat": 45.745841,
    "lng": -74.0344207,
    "type": "farm",
    "website": null
  },
  {
    "id": "node/8532154130",
    "name": "Ferme Marineau",
    "lat": 45.5214368,
    "lng": -73.7927461,
    "type": "farm",
    "website": null
  },
  {
    "id": "node/8547084155",
    "name": "Leopoldo Fruits & Vegetables",
    "lat": 45.535295,
    "lng": -73.6146311,
    "type": "farm",
    "website": "https://www.leopoldo.ca/"
  },
  {
    "id": "node/8668653020",
    "name": "Verger Coeur-de-Pomme",
    "lat": 45.5016332,
    "lng": -74.0374076,
    "type": "farm",
    "website": null
  },
  {
    "id": "node/8668653021",
    "name": "Verger Saab",
    "lat": 45.5022323,
    "lng": -74.0391852,
    "type": "farm",
    "website": null
  },
  {
    "id": "node/8790173399",
    "name": "Verger Yvan des Pommes",
    "lat": 45.5020815,
    "lng": -74.0015297,
    "type": "farm",
    "website": null
  },
  {
    "id": "node/8790264731",
    "name": "Cueillette 640",
    "lat": 45.5206026,
    "lng": -73.9912064,
    "type": "farm",
    "website": null
  },
  {
    "id": "node/8790264732",
    "name": "Le Pomiculteur du Bûcheron",
    "lat": 45.5217905,
    "lng": -73.990817,
    "type": "farm",
    "website": null
  },
  {
    "id": "node/8790619405",
    "name": "L'Érapom Lemaire",
    "lat": 45.5040287,
    "lng": -74.0087599,
    "type": "farm",
    "website": null
  },
  {
    "id": "node/8790651414",
    "name": "H et Y Gemme",
    "lat": 45.5014114,
    "lng": -74.0116522,
    "type": "farm",
    "website": null
  },
  {
    "id": "node/8790679261",
    "name": "Le Verger Trottier",
    "lat": 45.502897,
    "lng": -74.0057988,
    "type": "farm",
    "website": null
  },
  {
    "id": "node/8791686240",
    "name": "Verger Sylvain Lavallée",
    "lat": 45.5046448,
    "lng": -73.9979656,
    "type": "farm",
    "website": null
  },
  {
    "id": "node/8791944079",
    "name": "Verger Lavallée",
    "lat": 45.5124582,
    "lng": -73.9943306,
    "type": "farm",
    "website": null
  },
  {
    "id": "node/8791944081",
    "name": "Verger Richard Legault",
    "lat": 45.5099128,
    "lng": -73.9951413,
    "type": "farm",
    "website": null
  },
  {
    "id": "node/8791944276",
    "name": "À la croisée des pommes - Verger Bio",
    "lat": 45.5187973,
    "lng": -73.9914868,
    "type": "farm",
    "website": null
  },
  {
    "id": "node/8994476926",
    "name": "Bleu Lavande",
    "lat": 45.283943,
    "lng": -72.1919332,
    "type": "farm",
    "website": null
  },
  {
    "id": "node/8994521226",
    "name": "verger NNMA (Pomme en Fête)",
    "lat": 48.0690265,
    "lng": -66.7119926,
    "type": "farm",
    "website": null
  },
  {
    "id": "node/9015236188",
    "name": "Ferme coopérative Tourne-Sol",
    "lat": 45.3432454,
    "lng": -74.1383267,
    "type": "farm",
    "website": "https://www.fermetournesol.qc.ca"
  },
  {
    "id": "node/9324880854",
    "name": "La Barik",
    "lat": 46.3572255,
    "lng": -72.5863721,
    "type": "distillery",
    "website": "https://labarik.com/"
  },
  {
    "id": "node/9400905246",
    "name": "Distillerie des Marigots",
    "lat": 48.0894401,
    "lng": -65.6374283,
    "type": "distillery",
    "website": null
  },
  {
    "id": "node/9412773396",
    "name": "Distillerie du quai",
    "lat": 46.3324719,
    "lng": -72.5123618,
    "type": "distillery",
    "website": "https://www.distillerieduquai.com/"
  },
  {
    "id": "node/9450668522",
    "name": "Érablière Brunelle",
    "lat": 45.2950029,
    "lng": -72.6959613,
    "type": "farm",
    "website": null
  },
  {
    "id": "node/9463035906",
    "name": "Vignoble d'Ovila",
    "lat": 45.3710317,
    "lng": -74.1083162,
    "type": "winery",
    "website": null
  },
  {
    "id": "node/9463286477",
    "name": "Verger Barry",
    "lat": 46.5927143,
    "lng": -72.1275685,
    "type": "farm",
    "website": "https://www.vergerbarry.com/"
  },
  {
    "id": "node/9463286494",
    "name": "Verger Sauvageau",
    "lat": 46.5899123,
    "lng": -72.1311557,
    "type": "farm",
    "website": null
  },
  {
    "id": "node/9463335358",
    "name": "Verger Mayrand Kiosque De La Pomme",
    "lat": 46.5886502,
    "lng": -72.1392391,
    "type": "farm",
    "website": null
  },
  {
    "id": "node/9463456003",
    "name": "Le Garage - Microbrasserie",
    "lat": 46.5591788,
    "lng": -72.2146715,
    "type": "distillery",
    "website": null
  },
  {
    "id": "node/9601914534",
    "name": "Distillerie Vent du Nord",
    "lat": 49.226196,
    "lng": -68.1914458,
    "type": "distillery",
    "website": null
  },
  {
    "id": "node/9627589313",
    "name": "Terre-Mère, maraîcher biologique",
    "lat": 45.2920109,
    "lng": -73.2102513,
    "type": "farm",
    "website": "https://www.terre-mere.ca/"
  },
  {
    "id": "node/9627590147",
    "name": "Ferme Ammerlaan",
    "lat": 45.1187251,
    "lng": -73.3263085,
    "type": "farm",
    "website": null
  },
  {
    "id": "node/9629200180",
    "name": "Les Légumes Charbonneau",
    "lat": 45.4065554,
    "lng": -73.1093118,
    "type": "farm",
    "website": null
  },
  {
    "id": "node/9629215552",
    "name": "Domaine Valton Osiris",
    "lat": 45.5035103,
    "lng": -73.224408,
    "type": "farm",
    "website": "http://www.domainevaltonosiris.com/coordonnees.html"
  },
  {
    "id": "node/9631569077",
    "name": "Havre Vert",
    "lat": 45.5256616,
    "lng": -73.2336008,
    "type": "farm",
    "website": null
  },
  {
    "id": "node/9664109844",
    "name": "Les Jardins Carya",
    "lat": 45.4409919,
    "lng": -73.9514915,
    "type": "farm",
    "website": null
  },
  {
    "id": "node/9709092635",
    "name": "Vignoble Le Fief de la Rivière",
    "lat": 46.2517485,
    "lng": -72.5355177,
    "type": "winery",
    "website": null
  },
  {
    "id": "node/9908328001",
    "name": "Vignoble Domaine DesDuc",
    "lat": 47.3735905,
    "lng": -79.4920742,
    "type": "winery",
    "website": null
  },
  {
    "id": "node/9975569118",
    "name": "La Maison de la prune",
    "lat": 47.6934952,
    "lng": -69.6981952,
    "type": "farm",
    "website": null
  },
  {
    "id": "node/10153637466",
    "name": "Dans la Musette",
    "lat": 46.1299811,
    "lng": -74.1802681,
    "type": "farm",
    "website": null
  },
  {
    "id": "node/10292264105",
    "name": "Vergers Arsène Poisson",
    "lat": 45.4808636,
    "lng": -73.0916432,
    "type": "farm",
    "website": "https://chemindessept.ca/"
  },
  {
    "id": "node/10559226008",
    "name": "Vignoble J.O. Montpetit & Fils",
    "lat": 45.2486764,
    "lng": -73.9127989,
    "type": "winery",
    "website": null
  },
  {
    "id": "node/10560584863",
    "name": "Vignoble du Marathonien",
    "lat": 45.0456164,
    "lng": -73.7883203,
    "type": "winery",
    "website": null
  },
  {
    "id": "node/10682137753",
    "name": "Mielerie du cratère",
    "lat": 47.5247955,
    "lng": -70.2270463,
    "type": "farm",
    "website": null
  },
  {
    "id": "node/10775285545",
    "name": "Vignoble Clos Ste-Coix",
    "lat": 45.1327445,
    "lng": -72.8008288,
    "type": "winery",
    "website": null
  },
  {
    "id": "node/10775371912",
    "name": "Verger Canard Goûteux",
    "lat": 45.9682545,
    "lng": -71.9777921,
    "type": "farm",
    "website": null
  },
  {
    "id": "node/10822288273",
    "name": "Distillerie du Saint-Laurent",
    "lat": 48.5153516,
    "lng": -68.4679058,
    "type": "distillery",
    "website": "https://www.distilleriedustlaurent.com/"
  },
  {
    "id": "node/10893068371",
    "name": "Vignoble côte des limousins",
    "lat": 45.4162392,
    "lng": -72.609721,
    "type": "winery",
    "website": null
  },
  {
    "id": "node/11007476642",
    "name": "Ferme Michel Lauzon",
    "lat": 45.7216739,
    "lng": -73.9538311,
    "type": "farm",
    "website": null
  },
  {
    "id": "node/11075001751",
    "name": "Complexe touristique du bleuet",
    "lat": 48.6779167,
    "lng": -71.5405913,
    "type": "farm",
    "website": "https://complexetouristiquebleuet.com"
  },
  {
    "id": "node/11078493301",
    "name": "Vignoble Souffle de Vie",
    "lat": 45.4240911,
    "lng": -73.9675134,
    "type": "winery",
    "website": null
  },
  {
    "id": "node/11110230206",
    "name": "Terre Fruitière",
    "lat": 45.5118059,
    "lng": -73.4328511,
    "type": "farm",
    "website": "https://terrefruitiere.ca"
  },
  {
    "id": "node/11199140589",
    "name": "Ferme Hirondelle",
    "lat": 46.6535634,
    "lng": -70.1481208,
    "type": "farm",
    "website": null
  },
  {
    "id": "node/11199140590",
    "name": "Érablière Camille Bilodeau",
    "lat": 46.6365779,
    "lng": -70.1205417,
    "type": "farm",
    "website": null
  },
  {
    "id": "node/11227849641",
    "name": "151 Rang Sainte-Marie",
    "lat": 46.638342,
    "lng": -70.1705515,
    "type": "farm",
    "website": null
  },
  {
    "id": "node/11230013807",
    "name": "Ferme aux Colibris",
    "lat": 45.7209312,
    "lng": -75.1441041,
    "type": "farm",
    "website": "https://www.facebook.com/auxcolibris"
  },
  {
    "id": "node/11258192354",
    "name": "Verger Poméloi",
    "lat": 47.2407187,
    "lng": -61.9449983,
    "type": "apple",
    "website": null
  },
  {
    "id": "node/11268085105",
    "name": "Verger Fleuripom",
    "lat": 45.5271711,
    "lng": -73.9958704,
    "type": "farm",
    "website": null
  },
  {
    "id": "node/11292120159",
    "name": "Verger Joannette",
    "lat": 45.5241585,
    "lng": -73.9938214,
    "type": "farm",
    "website": null
  },
  {
    "id": "node/11695082651",
    "name": "Au Vignoble d'Orford",
    "lat": 45.3107137,
    "lng": -72.1446817,
    "type": "winery",
    "website": null
  },
  {
    "id": "node/11867215626",
    "name": "Au Pavillon de la Pomme",
    "lat": 45.5789138,
    "lng": -73.1666809,
    "type": "farm",
    "website": "https://www.pavillondelapomme.com/"
  },
  {
    "id": "node/11950450471",
    "name": "Le Kiosque Racíne",
    "lat": 45.752838,
    "lng": -73.7797406,
    "type": "farm",
    "website": "https://racinepetitsfruits.com/"
  },
  {
    "id": "node/11986525930",
    "name": "Vignoble Domaine Bresee",
    "lat": 45.148865,
    "lng": -72.6128711,
    "type": "winery",
    "website": null
  },
  {
    "id": "node/11989002761",
    "name": "Bleuets du Massif Sutton",
    "lat": 45.0649993,
    "lng": -72.6431701,
    "type": "farm",
    "website": null
  },
  {
    "id": "node/12022658312",
    "name": "Vignoble Bromont",
    "lat": 45.2530761,
    "lng": -72.7357027,
    "type": "winery",
    "website": null
  },
  {
    "id": "node/12022658379",
    "name": "Vignoble du PicBois",
    "lat": 45.2521613,
    "lng": -72.7100806,
    "type": "winery",
    "website": null
  },
  {
    "id": "node/12138131811",
    "name": "Distillerie Cap-aux-Péchés",
    "lat": 49.2247842,
    "lng": -65.9031101,
    "type": "distillery",
    "website": null
  },
  {
    "id": "node/12368270202",
    "name": "Ferme l'oiseau bleu",
    "lat": 47.4283157,
    "lng": -70.5103851,
    "type": "farm",
    "website": "https://www.fermeoiseaubleu.com/"
  },
  {
    "id": "node/12420604501",
    "name": "La Ferme de l'Aube",
    "lat": 45.957645,
    "lng": -74.858129,
    "type": "farm",
    "website": "https://www.lafermedelaube.com/"
  },
  {
    "id": "node/12420604601",
    "name": "MacCuaig Family Farm",
    "lat": 45.3853256,
    "lng": -74.4110282,
    "type": "farm",
    "website": null
  },
  {
    "id": "node/12489361345",
    "name": "Vignoble La Manse",
    "lat": 45.4474677,
    "lng": -72.6287612,
    "type": "winery",
    "website": null
  },
  {
    "id": "node/12594406773",
    "name": "Les jardins d'Oka",
    "lat": 45.5066861,
    "lng": -74.049795,
    "type": "farm",
    "website": null
  },
  {
    "id": "node/12605225019",
    "name": "Bleu sucré",
    "lat": 45.4921526,
    "lng": -74.0861333,
    "type": "farm",
    "website": null
  },
  {
    "id": "node/12647741330",
    "name": "Cherry River Distillerie",
    "lat": 45.2677592,
    "lng": -72.1523042,
    "type": "distillery",
    "website": null
  },
  {
    "id": "node/12811720250",
    "name": "Le Château Taillefer Lafon - Vignoble & Cidrerie",
    "lat": 45.5510738,
    "lng": -73.8233467,
    "type": "winery",
    "website": null
  }
]